demo/__init__.py
demo/local_settings.py
demo/models.py
demo/sass_variables.py
demo/settings.py
demo/urls.py
demo/views.py
demo/wsgi.py
demo/migrations/0001_initial.py
demo/migrations/0002_alter_demoone_date_created.py
demo/migrations/0003_auto_20220810_1650.py
demo/migrations/__init__.py
psu_export/__init__.py
psu_export/admin.py
psu_export/apps.py
psu_export/models.py
psu_export/urls.py
psu_export/views.py
psu_export/migrations/0001_initial.py
psu_export/migrations/0002_alter_exportfield_key.py
psu_export/migrations/0003_auto_20220823_1444.py
psu_export/migrations/__init__.py
psu_export/services/__init__.py
psu_export/services/export_service.py
psu_export/templates/psu_export/_app_definition.html
psu_export/templates/psu_export/_field_definition.html
psu_export/templates/psu_export/_model_definition.html
psu_export/templates/psu_export/export_status.html
psu_export/templates/psu_export/manage.js
psu_export/templatetags/__init__.py
psu_export/templatetags/export_taglib.py
psu_export/tests/__init__.py
psu_export/tests/test_applications.py
psu_export-3.0.9.dist-info/METADATA
psu_export-3.0.9.dist-info/WHEEL
psu_export-3.0.9.dist-info/top_level.txt
psu_export-3.0.9.dist-info/RECORD
